Metadata-Version: 2.1
Name: odoo12-addon-l10n-es-facturae-efact
Version: 12.0.1.0.3
Summary: Envío de Factura-e a e.FACT
Home-page: https://github.com/OCA/l10n-spain
Author: Creu Blanca, Odoo Community Association (OCA)
Author-email: support@odoo-community.org
License: AGPL-3
Platform: UNKNOWN
Classifier: Programming Language :: Python
Classifier: Framework :: Odoo
Classifier: License :: OSI Approved :: GNU Affero General Public License v3
Requires-Python: >=3.5
Requires-Dist: odoo12-addon-l10n-es-facturae
Requires-Dist: odoo (<12.1dev,>=12.0a)
Requires-Dist: paramiko
Requires-Dist: pyOpenSSL
Requires-Dist: xmlsec
